mnist/__init__.py
mnist/mnist.py
get_mnist-1.0.1.dist-info/LICENSE.txt
get_mnist-1.0.1.dist-info/METADATA
get_mnist-1.0.1.dist-info/WHEEL
get_mnist-1.0.1.dist-info/entry_points.txt
get_mnist-1.0.1.dist-info/top_level.txt
get_mnist-1.0.1.dist-info/RECORD
