Metadata-Version: 2.1
Name: get-mnist
Version: 1.0.1
Summary: Low Dependency Fetching of MNIST dataset
Home-page: https://github.com/blester125/get-mnist
Author: blester125
Author-email: blester125@gmail.com
License: MIT
Download-URL: https://github.com/blester125/get-mnist/archive/1.0.1.tar.gz
Keywords: MNIST,Machine Learning,Datasets
Platform: UNKNOWN
Classifier: Intended Audience :: Developers
Classifier: Natural Language :: English
Classifier: License :: OSI Approved :: MIT License
Classifier: Intended Audience :: Science/Research
Classifier: Development Status :: 3 - Alpha
Classifier: Topic :: Scientific/Engineering
Classifier: Environment :: Console
Requires-Dist: six
Requires-Dist: numpy
Provides-Extra: test
Requires-Dist: pytest ; extra == 'test'
Requires-Dist: mock ; extra == 'test'
